MANIFEST.in
README
setup.cfg
setup.py
sphinxcontrib/__init__.py
sphinxcontrib/mockautodoc.py
sphinxcontrib_mockautodoc.egg-info/PKG-INFO
sphinxcontrib_mockautodoc.egg-info/SOURCES.txt
sphinxcontrib_mockautodoc.egg-info/dependency_links.txt
sphinxcontrib_mockautodoc.egg-info/namespace_packages.txt
sphinxcontrib_mockautodoc.egg-info/not-zip-safe
sphinxcontrib_mockautodoc.egg-info/requires.txt
sphinxcontrib_mockautodoc.egg-info/top_level.txt
tests/test_functional.py
tests/fixture/conf.py
tests/fixture/index.rst
tests/fixture/_static/.placeholder
tests/fixture/app/package/__init__.py
tests/fixture/app/package/module.py