Metadata-Version: 1.1
Name: sphinxcontrib-mockautodoc
Version: 0.0.1dev-20130331
Summary: Sphinx mocking autodoc extension
Home-page: http://bitbucket.org/birkenfeld/sphinx-contrib
Author: Evgeniy Tatarkin
Author-email: tatarkin.evg@gmail.com
License: BSD
Download-URL: http://pypi.python.org/pypi/sphinxcontrib-mockautodoc
Platform: any
Classifier: Development Status :: 4 - Beta
Classifier: Environment :: Console
Classifier: Intended Audience :: Developers
Classifier: License :: OSI Approved :: BSD License
Classifier: Operating System :: OS Independent
Classifier: Programming Language :: Python
Classifier: Programming Language :: Python :: 2
Classifier: Programming Language :: Python :: 3
Classifier: Topic :: Documentation
Classifier: Topic :: Utilities
